[
  {
    "Party": "Bharatiya Janata Party - BJP",
    "Won": "240",
    "Leading": "0",
    "Total": "240"
  },
  {
    "Party": "Indian National Congress - INC",
    "Won": "99",
    "Leading": "0",
    "Total": "99"
  },
  {
    "Party": "Samajwadi Party - SP",
    "Won": "37",
    "Leading": "0",
    "Total": "37"
  },
  {
    "Party": "All India Trinamool Congress - AITC",
    "Won": "29",
    "Leading": "0",
    "Total": "29"
  },
  {
    "Party": "Dravida Munnetra Kazhagam - DMK",
    "Won": "22",
    "Leading": "0",
    "Total": "22"
  },
  {
    "Party": "Telugu Desam - TDP",
    "Won": "16",
    "Leading": "0",
    "Total": "16"
  },
  {
    "Party": "Janata Dal  (United) - JD(U)",
    "Won": "12",
    "Leading": "0",
    "Total": "12"
  },
  {
    "Party": "Shiv Sena (Uddhav Balasaheb Thackrey) - SHSUBT",
    "Won": "9",
    "Leading": "0",
    "Total": "9"
  },
  {
    "Party": "Nationalist Congress Party – Sharadchandra Pawar - NCPSP",
    "Won": "8",
    "Leading": "0",
    "Total": "8"
  },
  {
    "Party": "Shiv Sena - SHS",
    "Won": "7",
    "Leading": "0",
    "Total": "7"
  },
  {
    "Party": "Lok Janshakti Party(Ram Vilas) - LJPRV",
    "Won": "5",
    "Leading": "0",
    "Total": "5"
  },
  {
    "Party": "Yuvajana Sramika Rythu Congress Party - YSRCP",
    "Won": "4",
    "Leading": "0",
    "Total": "4"
  },
  {
    "Party": "Rashtriya Janata Dal - RJD",
    "Won": "4",
    "Leading": "0",
    "Total": "4"
  },
  {
    "Party": "Communist Party of India  (Marxist) - CPI(M)",
    "Won": "4",
    "Leading": "0",
    "Total": "4"
  },
  {
    "Party": "Indian Union Muslim League - IUML",
    "Won": "3",
    "Leading": "0",
    "Total": "3"
  },
  {
    "Party": "Aam Aadmi Party - AAAP",
    "Won": "3",
    "Leading": "0",
    "Total": "3"
  },
  {
    "Party": "Jharkhand Mukti Morcha - JMM",
    "Won": "3",
    "Leading": "0",
    "Total": "3"
  },
  {
    "Party": "Janasena Party - JnP",
    "Won": "2",
    "Leading": "0",
    "Total": "2"
  },
  {
    "Party": "Communist Party of India  (Marxist-Leninist)  (Liberation) - CPI(ML)(L)",
    "Won": "2",
    "Leading": "0",
    "Total": "2"
  },
  {
    "Party": "Janata Dal  (Secular) - JD(S)",
    "Won": "2",
    "Leading": "0",
    "Total": "2"
  },
  {
    "Party": "Viduthalai Chiruthaigal Katchi - VCK",
    "Won": "2",
    "Leading": "0",
    "Total": "2"
  },
  {
    "Party": "Communist Party of India - CPI",
    "Won": "2",
    "Leading": "0",
    "Total": "2"
  },
  {
    "Party": "Rashtriya Lok Dal - RLD",
    "Won": "2",
    "Leading": "0",
    "Total": "2"
  },
  {
    "Party": "Jammu & Kashmir National Conference - JKN",
    "Won": "2",
    "Leading": "0",
    "Total": "2"
  },
  {
    "Party": "United People’s Party, Liberal - UPPL",
    "Won": "1",
    "Leading": "0",
    "Total": "1"
  },
  {
    "Party": "Asom Gana Parishad - AGP",
    "Won": "1",
    "Leading": "0",
    "Total": "1"
  },
  {
    "Party": "Hindustani Awam Morcha (Secular) - HAMS",
    "Won": "1",
    "Leading": "0",
    "Total": "1"
  },
  {
    "Party": "Kerala Congress - KEC",
    "Won": "1",
    "Leading": "0",
    "Total": "1"
  },
  {
    "Party": "Revolutionary Socialist Party - RSP",
    "Won": "1",
    "Leading": "0",
    "Total": "1"
  },
  {
    "Party": "Nationalist Congress Party - NCP",
    "Won": "1",
    "Leading": "0",
    "Total": "1"
  },
  {
    "Party": "Voice of the People Party - VOTPP",
    "Won": "1",
    "Leading": "0",
    "Total": "1"
  },
  {
    "Party": "Zoram People’s Movement - ZPM",
    "Won": "1",
    "Leading": "0",
    "Total": "1"
  },
  {
    "Party": "Shiromani Akali Dal - SAD",
    "Won": "1",
    "Leading": "0",
    "Total": "1"
  },
  {
    "Party": "Rashtriya Loktantrik Party - RLTP",
    "Won": "1",
    "Leading": "0",
    "Total": "1"
  },
  {
    "Party": "Bharat Adivasi Party - BHRTADVSIP",
    "Won": "1",
    "Leading": "0",
    "Total": "1"
  },
  {
    "Party": "Sikkim Krantikari Morcha - SKM",
    "Won": "1",
    "Leading": "0",
    "Total": "1"
  },
  {
    "Party": "Marumalarchi Dravida Munnetra Kazhagam - MDMK",
    "Won": "1",
    "Leading": "0",
    "Total": "1"
  },
  {
    "Party": "Aazad Samaj Party (Kanshi Ram) - ASPKR",
    "Won": "1",
    "Leading": "0",
    "Total": "1"
  },
  {
    "Party": "Apna Dal (Soneylal) - ADAL",
    "Won": "1",
    "Leading": "0",
    "Total": "1"
  },
  {
    "Party": "AJSU Party - AJSUP",
    "Won": "1",
    "Leading": "0",
    "Total": "1"
  },
  {
    "Party": "All India Majlis-E-Ittehadul Muslimeen - AIMIM",
    "Won": "1",
    "Leading": "0",
    "Total": "1"
  },
  {
    "Party": "Independent - IND",
    "Won": "7",
    "Leading": "0",
    "Total": "7"
  }
]
